MANIFEST.in
requirements.txt
setup.cfg
setup.py
glvq/__init__.py
glvq/glvq.py
glvq/gmlvq.py
glvq/grlvq.py
glvq/lgmlvq.py
glvq/plot_2d.py
sklearn_glvq.egg-info/PKG-INFO
sklearn_glvq.egg-info/SOURCES.txt
sklearn_glvq.egg-info/dependency_links.txt
sklearn_glvq.egg-info/requires.txt
sklearn_glvq.egg-info/top_level.txt