Metadata-Version: 1.1
Name: sklearn-glvq
Version: 1.0.2
Summary: sklearn compatible Generalized Learning Vector Quantization implementation
Home-page: https://github.com/MrNuggelz/sklearn-glvq
Author: Joris Jensen
Author-email: jjensen@techfak.uni-bielefeld.de
License: BSD-3-Clause
Download-URL: https://github.com/MrNuggelz/sklearn-glvq/releases/tag/1.0.2
Platform: any
Classifier: Programming Language :: Python
Classifier: Programming Language :: Python :: 2.7
Classifier: Programming Language :: Python :: 3.5
Classifier: Intended Audience :: Science/Research
Classifier: Natural Language :: English
Classifier: Operating System :: POSIX
Classifier: Operating System :: MacOS
Classifier: Operating System :: Unix
Classifier: Operating System :: Microsoft :: Windows
